dirflex/__init__.py
dirflex/cli.py
dirflex/core.py
dirflex-0.1.6.dist-info/entry_points.txt
dirflex-0.1.6.dist-info/LICENSE
dirflex-0.1.6.dist-info/METADATA
dirflex-0.1.6.dist-info/WHEEL
dirflex-0.1.6.dist-info/RECORD
