Metadata-Version: 2.3
Name: dirflex
Version: 0.1.6
Summary: Flexible bidirectional directory tree parser & generator
License: MIT
Author: muhammadjalaludin
Author-email: 142960872+muhammadjalaludin@users.noreply.github.com
Requires-Python: >=3.10
Classifier: License :: OSI Approved :: MIT License
Classifier: Programming Language :: Python :: 3
Classifier: Programming Language :: Python :: 3.10
Classifier: Programming Language :: Python :: 3.11
Classifier: Programming Language :: Python :: 3.12
Classifier: Programming Language :: Python :: 3.13
Requires-Dist: rich (>=14.1.0,<15.0.0)
